coinaddr/__init__.py
coinaddr/base.py
coinaddr/currency.py
coinaddr/interfaces.py
coinaddr/validation.py
coinaddr-1.0.1.dist-info/LICENSE.txt
coinaddr-1.0.1.dist-info/METADATA
coinaddr-1.0.1.dist-info/RECORD
coinaddr-1.0.1.dist-info/WHEEL
coinaddr-1.0.1.dist-info/top_level.txt
tests/__init__.py
tests/test_coinaddr.py
tests/test_currency.py
tests/test_validation.py
