Metadata-Version: 2.1
Name: coinaddr
Version: 1.0.1
Summary: A crypto-currency address inspection/validation library.
Home-page: https://github.com/joeblackwaslike/coinaddr
Author: Joe Black
Author-email: me@joeblack.nyc
Maintainer: Joe Black
Maintainer-email: me@joeblack.nyc
License: MIT
Download-URL: https://github.com/joeblackwaslike/coinaddr/tarball/v1.0.1
Keywords: bitcoin,litecoin,altcoin,ethereum,address,validation,inspection
Platform: UNKNOWN
Classifier: Development Status :: 4 - Beta
Classifier: Intended Audience :: Developers
Classifier: Operating System :: OS Independent
Classifier: Natural Language :: English
Classifier: License :: OSI Approved :: MIT License
Classifier: Programming Language :: Python :: 3
Classifier: Programming Language :: Python :: 3.4
Classifier: Programming Language :: Python :: 3.5
Classifier: Programming Language :: Python :: 3.6
Classifier: Programming Language :: Python :: 3 :: Only
Classifier: Topic :: Internet :: WWW/HTTP
Classifier: Topic :: Software Development
Classifier: Topic :: Security :: Cryptography
Classifier: Topic :: Text Processing
Classifier: Topic :: Utilities
Classifier: Topic :: Software Development :: Libraries :: Python Modules
Requires-Dist: attrs (>=17.4.0)
Requires-Dist: pysha3 (>=1.0.2)
Requires-Dist: base58check (>=1.0.1)
Requires-Dist: zope.interface (>=4.4.3)
